ex2/uart_led_btn/hdl/debounce.sv
module debounce #(
  parameter integer unsigned CLK_FREQ = 50_000_000, // Clock frequency in [Hz]
  parameter real DEBOUNCE_TIME = 1.0,  // Debounce time in [ms]
  parameter logic DEBOUNCE_INIT = 1'b0 // Initial (Idle) value (also reset-polarity) of the debounced output after reset
)(
  input  wire  arst_n_i, // Asynchronous reset (active low)
  input  wire  clk_i,    // Clock input
  input  wire  din_i,    // Raw digital input - active level does not matter
  output logic deb_o     // Debounced digital input - active level does not matter
);

// Calculate the number of clock cycles for the debounce time
localparam integer unsigned DEBOUNCE_CYCLES = (CLK_FREQ / 1000) * DEBOUNCE_TIME;
localparam integer unsigned DEBOUNCE_WIDTH = $clog2(DEBOUNCE_CYCLES + 1);

// Internal signals
logic deb_sync_0 = 1'b0;
logic deb_sync_1 = 1'b1; // Note: Initialized to opposite value of deb_sync_0 to ensure proper operation after reset
logic [DEBOUNCE_WIDTH-1:0] deb_counter = '0;

// Synchronize the digital input to the clock domain - note the two-stage synchronizer and that it supposed to work with any input active level (high or low)
always_ff @(negedge arst_n_i, posedge clk_i) begin
  if (arst_n_i != 1'b1) begin // Asynchronous reset - just pass through the input (bypass the debounce logic)
    deb_sync_0 <= 1'b0; // First stage of synchronization - assign '0' on reset and ...
    deb_sync_1 <= 1'b1; // ... for the second stage of synchronization - assign '1' on reset. Thus ensuring that, no matter the debouncer config, the two stages are different after reset, so that the counter logic will start working properly.
    deb_o <= DEBOUNCE_INIT; // But, for the output - initialize it to the specified initial value. This will ensure known (idle) state after reset, but also that, no matter what the initial value (type of polarity) is configured for the debouncer, and what the actual input value is actually incomming, ...
    deb_counter <= '0; // ... its counter will always start from 0 and be counting the same ways, for the different configurations. So, after reset, the debouncer shall start outputting its preset initial value and it will hold it, till the time delay have passed - in order to change the output state.
  end else begin
    deb_sync_0 <= din_i; // First stage of synchronization
    deb_sync_1 <= deb_sync_0; // Second stage of synchronization
    if(deb_sync_1 != deb_sync_0) begin // if input changed, reset the counter
      deb_counter <= '0; // Reset the counter
    end else begin // Input is stable - increment the counter and/or update the debounced output 
      if(deb_counter == DEBOUNCE_CYCLES - 2) begin // Debounce time has elapsed. Note: -2 because of the two-stage synchronizer delay one clock cycle is already counted (witdrawn).
        deb_o <= deb_sync_1; // Update the debounced output
      end else begin
        deb_counter <= deb_counter + 1'b1; // Increment the counter. 
      end
    end
  end
end

endmodule

ex2/uart_led_btn/hdl_tb/debounce_tb.sv
// Testbench for debounce module
`timescale 1ns / 1ps // Note: the simulation time unit must be set to 1 [ns]

module debounce_tb;

  // =============================================================================
  // TESTBENCH PARAMETERS AND CONSTANTS
  // =============================================================================
  // Testbench parameters - matching DUT's:
  localparam CLK_FREQ = 50_000_000; // External Clock source, in [Hz]
  localparam CLK_PERIOD = 20;       // External Clock source, in [ns]
  localparam DEBOUNCE_TIME = 0.001;     // Debounce (Filter) time in [ms]
  // Testbench parameters - for simulation:
  localparam MAX_SIMULATION_TIME = 100_000_000; // Simulation time in [ns]
  localparam DEBOUNCE_CYCLES = (CLK_FREQ / 1000) * DEBOUNCE_TIME;
  // =============================================================================
  // TESTBENCH SIGNALS
  // =============================================================================
  // DUT signals:
  logic clk;      // Clock signal
  logic arst_n_i; // Asynchronous reset input - active low
  logic din_i;       // Input signal to be debounced
  logic deb_o_low;   // Debounced output signal - initial value '0'
  logic deb_o_high;  // Debounced output signal - initial value '1'
  // Testbench variables:
  int unsigned test_count = 0;
  int unsigned pass_count = 0;
  int unsigned fail_count = 0;

  // =============================================================================
  // CLOCK GENERATION
  // =============================================================================
  initial begin
    clk = 1'b0;
    forever #(CLK_PERIOD / 2) clk = ~clk; // Toggle clock every half period
  end   

  // =============================================================================
  // UNIT UNDER TEST (UUT) INSTANTIATION
  // =============================================================================
  // Dеbounce module instantiation - two instances with different initial values
  debounce #(
    .CLK_FREQ(CLK_FREQ),
    .DEBOUNCE_TIME(DEBOUNCE_TIME),
    .DEBOUNCE_INIT(1'b0)
  ) UUT_INIT_LOW (
    .arst_n_i(arst_n_i),
    .clk_i(clk),
    .din_i(din_i),
    .deb_o(deb_o_low)
  );

  debounce #(
    .CLK_FREQ(CLK_FREQ),
    .DEBOUNCE_TIME(DEBOUNCE_TIME),
    .DEBOUNCE_INIT(1'b1)
  ) UUT_INIT_HIGH (
    .arst_n_i(arst_n_i),
    .clk_i(clk),
    .din_i(din_i),
    .deb_o(deb_o_high)
  );

  // ============================================================================
  // TASKS AND FUNCTIONS
  // ============================================================================
  // Task to wait for a number of tb time units - not clock cycles
  task wait_period(input int num_time_units);
    #(num_time_units);
  endtask

  // Task to wait for a number of clock cycles
  task wait_cycles(input int num_cycles);
    repeat(num_cycles) @(posedge clk);
  endtask
  
  // Task to apply glitches (brief pulses)
  task apply_glitch(input logic value, input int duration_cycles);
    din_i = value;
    wait_cycles(duration_cycles);
    din_i = ~value;
  endtask
  
  // Task to check expected output
  task check_output(input logic expected_for_high, input logic expected_for_low, input string test_name);
    if((deb_o_high !== expected_for_high) || (deb_o_low !== expected_for_low)) begin
      $display("ERROR [%0t ns] %s: Expected deb_o_high=%b, deb_o_low=%b, got deb_o_high=%b, deb_o_low=%b", 
               $time, test_name, expected_for_high, expected_for_low, deb_o_high, deb_o_low);
      fail_count++;
    end else begin
      $display("PASS [%0t ns] %s: deb_o_high=%b and deb_o_low=%b as expected", 
               $time, test_name, deb_o_high, deb_o_low);
      pass_count++;
    end
  endtask

  // =============================================================================
  // TEST SEQUENCE
  // =============================================================================
  // Main test sequence
  initial begin  
    // Display testbench header information
    $display("========================================");
    $display("Debouncer Testbench Starting...");
    $display("========================================");
    $display("Clock Frequency: %0d [Hz]", CLK_FREQ);    
    $display("Clock Period: %0d [ns]", CLK_PERIOD);
    $display("Debounce Init Values: %s", "Both LOW and HIGH");
    $display("Debounce Time: %0d [ms]", DEBOUNCE_TIME);
    $display("");

    // Wait for a short time before starting tests - to observe initial conditions
    wait_period(CLK_PERIOD * 5); 

    // Initialize signals
    arst_n_i = 1'b1; // Assert reset
    din_i = 1'b0;    // Initial input value

    wait_cycles(10); // Wait for a few clock cycles

    // Test 1: Apply reset
    test_count++;
    $display("\n--- Test %0d: Reset Test ---", test_count);
    arst_n_i = 0;
    wait_cycles(5);
    check_output(1'b1, 1'b0, "Reset state"); // Reset values are asserted immediately.
    arst_n_i = 1; // Release reset
    wait_cycles(5); 
    check_output(1'b1, 1'b0, "After reset release"); // Should remain at initial values, still.

    // Test 2: Short glitches should be filtered out
    test_count++;
    $display("\n--- Test %0d: Glitch Filtering (short pulses) ---", test_count);
    din_i = 0;
    wait_cycles(10);
    
    // Apply several short glitches
    for (int i = 0; i < 5; i++) begin
      apply_glitch(1'b1, 3); // 3-cycle glitch
      wait_cycles(5);
    end
    wait_cycles(10);
    check_output(1'b0, 1'b0, "After short glitches");
    
    // Test 3: Stable transition from 0 to 1
    test_count++;
    $display("\n--- Test %0d: Clean Transition 0->1 ---", test_count);
    din_i = 0;
    wait_cycles(10);
    din_i = 1;
    
    // Should still be 0 before debounce completes
    wait_cycles(DEBOUNCE_CYCLES - 5);
    check_output(1'b0, 1'b0, "Before debounce complete");
    
    // Wait for debounce to complete
    wait_cycles(10);
    check_output(1'b1, 1'b1, "After debounce complete");
    
    // Test 4: Glitches during debouncing should restart counter
    test_count++;
    $display("\n--- Test %0d: Glitch During Debounce ---", test_count);
    din_i = 1;
    wait_cycles(10);
    din_i = 0; // Start transition to 0
    
    // Midway through debounce, apply a glitch
    wait_cycles(DEBOUNCE_CYCLES / 2);
    din_i = 1; // Glitch back to 1
    wait_cycles(5);
    din_i = 0; // Back to 0 (counter should restart)
    
    // Output should still be 1
    wait_cycles(DEBOUNCE_CYCLES - 10);
    check_output(1'b1, 1'b1, "Glitch restarted counter");
    
    // Now wait full debounce time
    wait_cycles(20);
    check_output(1'b0, 1'b0, "After full debounce from glitch");
    
    // Test 5: Stable transition from 1 to 0
    test_count++;
    $display("\n--- Test %0d: Clean Transition 1->0 ---", test_count);
    din_i = 0;
    wait_cycles(10);
    din_i = 1;
    wait_cycles(DEBOUNCE_CYCLES + 10);
    check_output(1'b1, 1'b1, "Stable at 1");
    
    din_i = 0;
    wait_cycles(DEBOUNCE_CYCLES + 10);
    check_output(1'b0, 1'b0, "Transitioned to 0");
    
    // Test 6: Multiple rapid transitions (bouncing)
    test_count++;
    $display("\n--- Test %0d: Rapid Bouncing ---", test_count);
    din_i = 0;
    wait_cycles(10);
    
    // Simulate button bouncing
    for (int i = 0; i < 10; i++) begin
      din_i = ~din_i;
      wait_cycles($urandom_range(5, 20));
    end
    din_i = 1; // Settle to 1
    
    wait_cycles(DEBOUNCE_CYCLES + 10);
    check_output(1'b1, 1'b1, "After bouncing settled to 1");
    
    // Test 7: Reset during debouncing
    test_count++;
    $display("\n--- Test %0d: Reset During Debounce ---", test_count);
    din_i = 1;
    wait_cycles(10);
    din_i = 0; // Start transition
    wait_cycles(DEBOUNCE_CYCLES / 2); // Halfway through
    
    arst_n_i = 0; // Apply reset
    wait_cycles(3);
    check_output(1'b1, 1'b1, "During reset");
    arst_n_i = 1;
    wait_cycles(5);
    check_output(1'b0, 1'b0, "After reset with din_i=0");
    
    // Test 8: Verify timing accuracy
    test_count++;
    $display("\n--- Test %0d: Timing Verification ---", test_count);
    din_i = 0;
    wait_cycles(20);
    
    din_i = 1;
    fork
      begin
        wait_cycles(DEBOUNCE_CYCLES - 3);
        if ((deb_o_high !== 1'b1) || (deb_o_low !== 1'b0)) begin
          $display("ERROR: Output changed too early");
          fail_count++;
        end
      end
      begin
        wait_cycles(DEBOUNCE_CYCLES + 5);
        if ((deb_o_high !== 1'b1) || (deb_o_low !== 1'b0)) begin
          $display("ERROR: Output didn't change in time");
          fail_count++;
        end else begin
          $display("PASS: Timing accurate");
        end
      end
    join
    
    wait_cycles(20);
    
    // Test Summary
    $display("\n========================================");
    $display("Testbench Completed. Summary: ");
    $display("========================================");
    $display("Total tests run: %0d", test_count);
    if (fail_count == 0) begin
      $display("Result: ALL TESTS PASSED!");
    end else begin
      $display("Result: %0d fail_count DETECTED", fail_count);
    end
    $display("========================================\n");
    
    $finish;
  end

  // =============================================================================
  // WAVEFORM DUMPING 
  // =============================================================================
  initial begin
    $dumpfile("debounce_tb.vcd");
    $dumpvars(0, debounce_tb);
  end

  // =============================================================================
  // TIMEOUT WATCHDOG
  // =============================================================================
 initial begin
    #(CLK_PERIOD * DEBOUNCE_CYCLES * 50); // Generous timeout
    $display("ERROR: Testbench timeout!");
    $finish;
  end


endmodule

ex2/uart_led_btn/simulation/questa/debounce_tb.vcd
$date
	Sun Jan 25 19:47:07 2026
$end
$version
	QuestaSim Version 2024.1
$end
$timescale
	1ps
$end

$scope module debounce_tb $end
$var parameter 32 ! CLK_FREQ $end
$var parameter 32 " CLK_PERIOD $end
$var parameter 0 # DEBOUNCE_TIME $end
$var parameter 32 $ MAX_SIMULATION_TIME $end
$var parameter 0 % DEBOUNCE_CYCLES $end
$var reg 1 & clk $end
$var reg 1 ' arst_n_i $end
$var reg 1 ( din_i $end
$var reg 1 ) deb_o_low $end
$var reg 1 * deb_o_high $end
$var integer 32 + test_count $end
$var integer 32 , pass_count $end
$var integer 32 - fail_count $end

$scope task wait_period $end
$var integer 32 . num_time_units $end
$upscope $end

$scope task wait_cycles $end
$var integer 32 / num_cycles $end
$upscope $end

$scope task apply_glitch $end
$var reg 1 0 value $end
$var integer 32 1 duration_cycles $end
$upscope $end

$scope task check_output $end
$var reg 1 2 expected_for_high $end
$var reg 1 3 expected_for_low $end
$upscope $end

$scope module UUT_INIT_LOW $end
$var parameter 32 4 CLK_FREQ $end
$var parameter 0 5 DEBOUNCE_TIME $end
$var parameter 1 6 DEBOUNCE_INIT $end
$var parameter 32 7 DEBOUNCE_CYCLES $end
$var parameter 32 8 DEBOUNCE_WIDTH $end
$var wire 1 9 arst_n_i $end
$var wire 1 : clk_i $end
$var wire 1 ; din_i $end
$var reg 1 < deb_o $end
$var reg 1 = deb_sync_0 $end
$var reg 1 > deb_sync_1 $end
$var reg 6 ? deb_counter [5:0] $end
$upscope $end

$scope module UUT_INIT_HIGH $end
$var parameter 32 @ CLK_FREQ $end
$var parameter 0 A DEBOUNCE_TIME $end
$var parameter 1 B DEBOUNCE_INIT $end
$var parameter 32 C DEBOUNCE_CYCLES $end
$var parameter 32 D DEBOUNCE_WIDTH $end
$var wire 1 E arst_n_i $end
$var wire 1 F clk_i $end
$var wire 1 G din_i $end
$var reg 1 H deb_o $end
$var reg 1 I deb_sync_0 $end
$var reg 1 J deb_sync_1 $end
$var reg 6 K deb_counter [5:0] $end
$upscope $end
$upscope $end
$enddefinitions $end
#0
$dumpvars
0&
x'
x(
x)
x*
x<
x=
x>
b0 ?
xH
xI
xJ
b0 K
x0
x2
x3
b10111110101111000010000000 !
b10100 "
b101111101011110000100000000 $
b10111110101111000010000000 4
b0 6
b110010 7
b110 8
b10111110101111000010000000 @
b1 B
b110010 C
b110 D
r0.001 #
r50 %
r0.001 5
r0.001 A
b0 +
b0 ,
b0 -
b1100100 .
b0 /
b0 1
xG
0F
xE
x;
0:
x9
$end
#10000
1&
1:
1F
b1 K
b1 ?
#20000
0&
0:
0F
#30000
1&
1:
1F
b10 K
b10 ?
#40000
0&
0:
0F
#50000
1&
1:
1F
b11 K
b11 ?
#60000
0&
0:
0F
#70000
1&
1:
1F
b100 K
b100 ?
#80000
0&
0:
0F
#90000
1&
1:
1F
b101 K
b101 ?
#100000
1'
0(
b1010 /
0&
0;
0G
19
1E
0:
0F
#110000
1&
1:
1F
0I
b110 K
0=
b110 ?
#120000
0&
0:
0F
#130000
1&
1:
1F
0J
b111 K
0>
b111 ?
#140000
0&
0:
0F
#150000
1&
1:
1F
b1000 K
b1000 ?
#160000
0&
0:
0F
#170000
1&
1:
1F
b1001 K
b1001 ?
#180000
0&
0:
0F
#190000
1&
1:
1F
b1010 K
b1010 ?
#200000
0&
0:
0F
#210000
1&
1:
1F
b1011 K
b1011 ?
#220000
0&
0:
0F
#230000
1&
1:
1F
b1100 K
b1100 ?
#240000
0&
0:
0F
#250000
1&
1:
1F
b1101 K
b1101 ?
#260000
0&
0:
0F
#270000
1&
1:
1F
b1110 K
b1110 ?
#280000
0&
0:
0F
#290000
1&
1:
1F
b1 +
0'
b101 /
09
0E
b1111 K
b1111 ?
1J
1H
b0 K
1>
0<
b0 ?
0)
1*
#300000
0&
0:
0F
#310000
1&
1:
1F
#320000
0&
0:
0F
#330000
1&
1:
1F
#340000
0&
0:
0F
#350000
1&
1:
1F
#360000
0&
0:
0F
#370000
1&
1:
1F
#380000
0&
0:
0F
#390000
1&
1:
1F
12
03
b1 ,
1'
19
1E
#400000
0&
0:
0F
#410000
1&
1:
1F
0J
0>
#420000
0&
0:
0F
#430000
1&
1:
1F
b1 K
b1 ?
#440000
0&
0:
0F
#450000
1&
1:
1F
b10 K
b10 ?
#460000
0&
0:
0F
#470000
1&
1:
1F
b11 K
b11 ?
#480000
0&
0:
0F
#490000
1&
1:
1F
b10 ,
b10 +
b1010 /
b100 K
b100 ?
#500000
0&
0:
0F
#510000
1&
1:
1F
b101 K
b101 ?
#520000
0&
0:
0F
#530000
1&
1:
1F
b110 K
b110 ?
#540000
0&
0:
0F
#550000
1&
1:
1F
b111 K
b111 ?
#560000
0&
0:
0F
#570000
1&
1:
1F
b1000 K
b1000 ?
#580000
0&
0:
0F
#590000
1&
1:
1F
b1001 K
b1001 ?
#600000
0&
0:
0F
#610000
1&
1:
1F
b1010 K
b1010 ?
#620000
0&
0:
0F
#630000
1&
1:
1F
b1011 K
b1011 ?
#640000
0&
0:
0F
#650000
1&
1:
1F
b1100 K
b1100 ?
#660000
0&
0:
0F
#670000
1&
1:
1F
b1101 K
b1101 ?
#680000
0&
0:
0F
#690000
1&
1:
1F
10
b11 1
1(
b11 /
1;
1G
b1110 K
b1110 ?
#700000
0&
0:
0F
#710000
1&
1:
1F
1I
b1111 K
1=
b1111 ?
#720000
0&
0:
0F
#730000
1&
1:
1F
1J
b0 K
1>
b0 ?
#740000
0&
0:
0F
#750000
1&
1:
1F
0(
b101 /
0;
0G
b1 K
b1 ?
#760000
0&
0:
0F
#770000
1&
1:
1F
0I
b10 K
0=
b10 ?
#780000
0&
0:
0F
#790000
1&
1:
1F
0J
b0 K
0>
b0 ?
#800000
0&
0:
0F
#810000
1&
1:
1F
b1 K
b1 ?
#820000
0&
0:
0F
#830000
1&
1:
1F
b10 K
b10 ?
#840000
0&
0:
0F
#850000
1&
1:
1F
1(
b11 /
1;
1G
b11 K
b11 ?
#860000
0&
0:
0F
#870000
1&
1:
1F
1I
b100 K
1=
b100 ?
#880000
0&
0:
0F
#890000
1&
1:
1F
1J
b0 K
1>
b0 ?
#900000
0&
0:
0F
#910000
1&
1:
1F
0(
b101 /
0;
0G
b1 K
b1 ?
#920000
0&
0:
0F
#930000
1&
1:
1F
0I
b10 K
0=
b10 ?
#940000
0&
0:
0F
#950000
1&
1:
1F
0J
b0 K
0>
b0 ?
#960000
0&
0:
0F
#970000
1&
1:
1F
b1 K
b1 ?
#980000
0&
0:
0F
#990000
1&
1:
1F
b10 K
b10 ?
#1000000
0&
0:
0F
#1010000
1&
1:
1F
1(
b11 /
1;
1G
b11 K
b11 ?
#1020000
0&
0:
0F
#1030000
1&
1:
1F
1I
b100 K
1=
b100 ?
#1040000
0&
0:
0F
#1050000
1&
1:
1F
1J
b0 K
1>
b0 ?
#1060000
0&
0:
0F
#1070000
1&
1:
1F
0(
b101 /
0;
0G
b1 K
b1 ?
#1080000
0&
0:
0F
#1090000
1&
1:
1F
0I
b10 K
0=
b10 ?
#1100000
0&
0:
0F
#1110000
1&
1:
1F
0J
b0 K
0>
b0 ?
#1120000
0&
0:
0F
#1130000
1&
1:
1F
b1 K
b1 ?
#1140000
0&
0:
0F
#1150000
1&
1:
1F
b10 K
b10 ?
#1160000
0&
0:
0F
#1170000
1&
1:
1F
1(
b11 /
1;
1G
b11 K
b11 ?
#1180000
0&
0:
0F
#1190000
1&
1:
1F
1I
b100 K
1=
b100 ?
#1200000
0&
0:
0F
#1210000
1&
1:
1F
1J
b0 K
1>
b0 ?
#1220000
0&
0:
0F
#1230000
1&
1:
1F
0(
b101 /
0;
0G
b1 K
b1 ?
#1240000
0&
0:
0F
#1250000
1&
1:
1F
0I
b10 K
0=
b10 ?
#1260000
0&
0:
0F
#1270000
1&
1:
1F
0J
b0 K
0>
b0 ?
#1280000
0&
0:
0F
#1290000
1&
1:
1F
b1 K
b1 ?
#1300000
0&
0:
0F
#1310000
1&
1:
1F
b10 K
b10 ?
#1320000
0&
0:
0F
#1330000
1&
1:
1F
1(
b11 /
1;
1G
b11 K
b11 ?
#1340000
0&
0:
0F
#1350000
1&
1:
1F
1I
b100 K
1=
b100 ?
#1360000
0&
0:
0F
#1370000
1&
1:
1F
1J
b0 K
1>
b0 ?
#1380000
0&
0:
0F
#1390000
1&
1:
1F
0(
b101 /
0;
0G
b1 K
b1 ?
#1400000
0&
0:
0F
#1410000
1&
1:
1F
0I
b10 K
0=
b10 ?
#1420000
0&
0:
0F
#1430000
1&
1:
1F
0J
b0 K
0>
b0 ?
#1440000
0&
0:
0F
#1450000
1&
1:
1F
b1 K
b1 ?
#1460000
0&
0:
0F
#1470000
1&
1:
1F
b10 K
b10 ?
#1480000
0&
0:
0F
#1490000
1&
1:
1F
b1010 /
b11 K
b11 ?
#1500000
0&
0:
0F
#1510000
1&
1:
1F
b100 K
b100 ?
#1520000
0&
0:
0F
#1530000
1&
1:
1F
b101 K
b101 ?
#1540000
0&
0:
0F
#1550000
1&
1:
1F
b110 K
b110 ?
#1560000
0&
0:
0F
#1570000
1&
1:
1F
b111 K
b111 ?
#1580000
0&
0:
0F
#1590000
1&
1:
1F
b1000 K
b1000 ?
#1600000
0&
0:
0F
#1610000
1&
1:
1F
b1001 K
b1001 ?
#1620000
0&
0:
0F
#1630000
1&
1:
1F
b1010 K
b1010 ?
#1640000
0&
0:
0F
#1650000
1&
1:
1F
b1011 K
b1011 ?
#1660000
0&
0:
0F
#1670000
1&
1:
1F
b1100 K
b1100 ?
#1680000
0&
0:
0F
#1690000
1&
1:
1F
02
b1 -
b11 +
b1101 K
b1101 ?
#1700000
0&
0:
0F
#1710000
1&
1:
1F
b1110 K
b1110 ?
#1720000
0&
0:
0F
#1730000
1&
1:
1F
b1111 K
b1111 ?
#1740000
0&
0:
0F
#1750000
1&
1:
1F
b10000 K
b10000 ?
#1760000
0&
0:
0F
#1770000
1&
1:
1F
b10001 K
b10001 ?
#1780000
0&
0:
0F
#1790000
1&
1:
1F
b10010 K
b10010 ?
#1800000
0&
0:
0F
#1810000
1&
1:
1F
b10011 K
b10011 ?
#1820000
0&
0:
0F
#1830000
1&
1:
1F
b10100 K
b10100 ?
#1840000
0&
0:
0F
#1850000
1&
1:
1F
b10101 K
b10101 ?
#1860000
0&
0:
0F
#1870000
1&
1:
1F
b10110 K
b10110 ?
#1880000
0&
0:
0F
#1890000
1&
1:
1F
1(
b101101 /
1;
1G
b10111 K
b10111 ?
#1900000
0&
0:
0F
#1910000
1&
1:
1F
1I
b11000 K
1=
b11000 ?
#1920000
0&
0:
0F
#1930000
1&
1:
1F
1J
b0 K
1>
b0 ?
#1940000
0&
0:
0F
#1950000
1&
1:
1F
b1 K
b1 ?
#1960000
0&
0:
0F
#1970000
1&
1:
1F
b10 K
b10 ?
#1980000
0&
0:
0F
#1990000
1&
1:
1F
b11 K
b11 ?
#2000000
0&
0:
0F
#2010000
1&
1:
1F
b100 K
b100 ?
#2020000
0&
0:
0F
#2030000
1&
1:
1F
b101 K
b101 ?
#2040000
0&
0:
0F
#2050000
1&
1:
1F
b110 K
b110 ?
#2060000
0&
0:
0F
#2070000
1&
1:
1F
b111 K
b111 ?
#2080000
0&
0:
0F
#2090000
1&
1:
1F
b1000 K
b1000 ?
#2100000
0&
0:
0F
#2110000
1&
1:
1F
b1001 K
b1001 ?
#2120000
0&
0:
0F
#2130000
1&
1:
1F
b1010 K
b1010 ?
#2140000
0&
0:
0F
#2150000
1&
1:
1F
b1011 K
b1011 ?
#2160000
0&
0:
0F
#2170000
1&
1:
1F
b1100 K
b1100 ?
#2180000
0&
0:
0F
#2190000
1&
1:
1F
b1101 K
b1101 ?
#2200000
0&
0:
0F
#2210000
1&
1:
1F
b1110 K
b1110 ?
#2220000
0&
0:
0F
#2230000
1&
1:
1F
b1111 K
b1111 ?
#2240000
0&
0:
0F
#2250000
1&
1:
1F
b10000 K
b10000 ?
#2260000
0&
0:
0F
#2270000
1&
1:
1F
b10001 K
b10001 ?
#2280000
0&
0:
0F
#2290000
1&
1:
1F
b10010 K
b10010 ?
#2300000
0&
0:
0F
#2310000
1&
1:
1F
b10011 K
b10011 ?
#2320000
0&
0:
0F
#2330000
1&
1:
1F
b10100 K
b10100 ?
#2340000
0&
0:
0F
#2350000
1&
1:
1F
b10101 K
b10101 ?
#2360000
0&
0:
0F
#2370000
1&
1:
1F
b10110 K
b10110 ?
#2380000
0&
0:
0F
#2390000
1&
1:
1F
b10111 K
b10111 ?
#2400000
0&
0:
0F
#2410000
1&
1:
1F
b11000 K
b11000 ?
#2420000
0&
0:
0F
#2430000
1&
1:
1F
b11001 K
b11001 ?
#2440000
0&
0:
0F
#2450000
1&
1:
1F
b11010 K
b11010 ?
#2460000
0&
0:
0F
#2470000
1&
1:
1F
b11011 K
b11011 ?
#2480000
0&
0:
0F
#2490000
1&
1:
1F
b11100 K
b11100 ?
#2500000
0&
0:
0F
#2510000
1&
1:
1F
b11101 K
b11101 ?
#2520000
0&
0:
0F
#2530000
1&
1:
1F
b11110 K
b11110 ?
#2540000
0&
0:
0F
#2550000
1&
1:
1F
b11111 K
b11111 ?
#2560000
0&
0:
0F
#2570000
1&
1:
1F
b100000 K
b100000 ?
#2580000
0&
0:
0F
#2590000
1&
1:
1F
b100001 K
b100001 ?
#2600000
0&
0:
0F
#2610000
1&
1:
1F
b100010 K
b100010 ?
#2620000
0&
0:
0F
#2630000
1&
1:
1F
b100011 K
b100011 ?
#2640000
0&
0:
0F
#2650000
1&
1:
1F
b100100 K
b100100 ?
#2660000
0&
0:
0F
#2670000
1&
1:
1F
b100101 K
b100101 ?
#2680000
0&
0:
0F
#2690000
1&
1:
1F
b100110 K
b100110 ?
#2700000
0&
0:
0F
#2710000
1&
1:
1F
b100111 K
b100111 ?
#2720000
0&
0:
0F
#2730000
1&
1:
1F
b101000 K
b101000 ?
#2740000
0&
0:
0F
#2750000
1&
1:
1F
b101001 K
b101001 ?
#2760000
0&
0:
0F
#2770000
1&
1:
1F
b101010 K
b101010 ?
#2780000
0&
0:
0F
#2790000
1&
1:
1F
b10 -
b1010 /
b101011 K
b101011 ?
#2800000
0&
0:
0F
#2810000
1&
1:
1F
b101100 K
b101100 ?
#2820000
0&
0:
0F
#2830000
1&
1:
1F
b101101 K
b101101 ?
#2840000
0&
0:
0F
#2850000
1&
1:
1F
b101110 K
b101110 ?
#2860000
0&
0:
0F
#2870000
1&
1:
1F
b101111 K
b101111 ?
#2880000
0&
0:
0F
#2890000
1&
1:
1F
b110000 K
b110000 ?
#2900000
0&
0:
0F
#2910000
1&
1:
1F
1<
1)
#2920000
0&
0:
0F
#2930000
1&
1:
1F
#2940000
0&
0:
0F
#2950000
1&
1:
1F
#2960000
0&
0:
0F
#2970000
1&
1:
1F
#2980000
0&
0:
0F
#2990000
1&
1:
1F
12
13
b11 ,
b100 +
#3000000
0&
0:
0F
#3010000
1&
1:
1F
#3020000
0&
0:
0F
#3030000
1&
1:
1F
#3040000
0&
0:
0F
#3050000
1&
1:
1F
#3060000
0&
0:
0F
#3070000
1&
1:
1F
#3080000
0&
0:
0F
#3090000
1&
1:
1F
#3100000
0&
0:
0F
#3110000
1&
1:
1F
#3120000
0&
0:
0F
#3130000
1&
1:
1F
#3140000
0&
0:
0F
#3150000
1&
1:
1F
#3160000
0&
0:
0F
#3170000
1&
1:
1F
#3180000
0&
0:
0F
#3190000
1&
1:
1F
0(
b11001 /
0;
0G
#3200000
0&
0:
0F
#3210000
1&
1:
1F
0I
0=
#3220000
0&
0:
0F
#3230000
1&
1:
1F
0J
b0 K
0>
b0 ?
#3240000
0&
0:
0F
#3250000
1&
1:
1F
b1 K
b1 ?
#3260000
0&
0:
0F
#3270000
1&
1:
1F
b10 K
b10 ?
#3280000
0&
0:
0F
#3290000
1&
1:
1F
b11 K
b11 ?
#3300000
0&
0:
0F
#3310000
1&
1:
1F
b100 K
b100 ?
#3320000
0&
0:
0F
#3330000
1&
1:
1F
b101 K
b101 ?
#3340000
0&
0:
0F
#3350000
1&
1:
1F
b110 K
b110 ?
#3360000
0&
0:
0F
#3370000
1&
1:
1F
b111 K
b111 ?
#3380000
0&
0:
0F
#3390000
1&
1:
1F
b1000 K
b1000 ?
#3400000
0&
0:
0F
#3410000
1&
1:
1F
b1001 K
b1001 ?
#3420000
0&
0:
0F
#3430000
1&
1:
1F
b1010 K
b1010 ?
#3440000
0&
0:
0F
#3450000
1&
1:
1F
b1011 K
b1011 ?
#3460000
0&
0:
0F
#3470000
1&
1:
1F
b1100 K
b1100 ?
#3480000
0&
0:
0F
#3490000
1&
1:
1F
b1101 K
b1101 ?
#3500000
0&
0:
0F
#3510000
1&
1:
1F
b1110 K
b1110 ?
#3520000
0&
0:
0F
#3530000
1&
1:
1F
b1111 K
b1111 ?
#3540000
0&
0:
0F
#3550000
1&
1:
1F
b10000 K
b10000 ?
#3560000
0&
0:
0F
#3570000
1&
1:
1F
b10001 K
b10001 ?
#3580000
0&
0:
0F
#3590000
1&
1:
1F
b10010 K
b10010 ?
#3600000
0&
0:
0F
#3610000
1&
1:
1F
b10011 K
b10011 ?
#3620000
0&
0:
0F
#3630000
1&
1:
1F
b10100 K
b10100 ?
#3640000
0&
0:
0F
#3650000
1&
1:
1F
b10101 K
b10101 ?
#3660000
0&
0:
0F
#3670000
1&
1:
1F
b10110 K
b10110 ?
#3680000
0&
0:
0F
#3690000
1&
1:
1F
1(
b101 /
1;
1G
b10111 K
b10111 ?
#3700000
0&
0:
0F
#3710000
1&
1:
1F
1I
b11000 K
1=
b11000 ?
#3720000
0&
0:
0F
#3730000
1&
1:
1F
1J
b0 K
1>
b0 ?
#3740000
0&
0:
0F
#3750000
1&
1:
1F
b1 K
b1 ?
#3760000
0&
0:
0F
#3770000
1&
1:
1F
b10 K
b10 ?
#3780000
0&
0:
0F
#3790000
1&
1:
1F
0(
b101000 /
0;
0G
b11 K
b11 ?
#3800000
0&
0:
0F
#3810000
1&
1:
1F
0I
b100 K
0=
b100 ?
#3820000
0&
0:
0F
#3830000
1&
1:
1F
0J
b0 K
0>
b0 ?
#3840000
0&
0:
0F
#3850000
1&
1:
1F
b1 K
b1 ?
#3860000
0&
0:
0F
#3870000
1&
1:
1F
b10 K
b10 ?
#3880000
0&
0:
0F
#3890000
1&
1:
1F
b11 K
b11 ?
#3900000
0&
0:
0F
#3910000
1&
1:
1F
b100 K
b100 ?
#3920000
0&
0:
0F
#3930000
1&
1:
1F
b101 K
b101 ?
#3940000
0&
0:
0F
#3950000
1&
1:
1F
b110 K
b110 ?
#3960000
0&
0:
0F
#3970000
1&
1:
1F
b111 K
b111 ?
#3980000
0&
0:
0F
#3990000
1&
1:
1F
b1000 K
b1000 ?
#4000000
0&
0:
0F
#4010000
1&
1:
1F
b1001 K
b1001 ?
#4020000
0&
0:
0F
#4030000
1&
1:
1F
b1010 K
b1010 ?
#4040000
0&
0:
0F
#4050000
1&
1:
1F
b1011 K
b1011 ?
#4060000
0&
0:
0F
#4070000
1&
1:
1F
b1100 K
b1100 ?
#4080000
0&
0:
0F
