ex2/uart_led_btn/hdl/reset_sync.sv
 /* This is a reset generation circuit - it provides asyncrhonously asserted, and  
  * and syncrhonously deasserted - reset signal, to any system flip flops that are 
  * asyncrhonously cleared or set in the FPGA. 
  *
  * Note: This circuit allows the Quartus II Application' TimeQuest analisys tool 
  * to accurately measure the recovery and removal timing to the sytem flops. 
  */
module reset_sync #(
  parameter RESET_POLARITY = "HIGH", // Reset polarity: "HIGH" for active high reset, "LOW" for active low reset
  parameter SYNC_STAGES = 2 // Number of synchronization stages. Expected values are 2 or more.
)(
  input  wire  async_rst_i,   // Asynchronous reset input
  input  wire  clk_i,         // Clock input
  output logic synced_rst_o   // Synchronized reset output
);


// Conditional hdl generation:
generate 
  if(RESET_POLARITY == "HIGH") begin : GEN_SYNC_ACTIVE_HIGH // If the reset is active-high
    logic [0:SYNC_STAGES-1] sync_ff = '1; // Synchronizer flip-flops. Note: Bit 0 is the last stage (MSb), Bit SYNC_STAGES-1 is the first stage (LSb). So no matter the number of stages, the last stage (synced) output is always sync_ff[0].
    always_ff @(posedge async_rst_i, posedge clk_i) begin 
      if(async_rst_i != 1'b0) begin  // Asynchronous part - assert reset
        sync_ff <= '1;
      end else begin // Synchronous part - shift in '0's - deasserting reset
        sync_ff <= {sync_ff[1:SYNC_STAGES-1], 1'b0}; // Shift left, inserting '0' at LSb
      end
    end
  end else if(RESET_POLARITY == "LOW") begin : GEN_SYNC_ACTIVE_LOW // If the reset is active-low
    logic [0:SYNC_STAGES-1] sync_ff = '0; // Synchronizer flip-flops. Note: Bit 0 is the last stage (MSb), Bit SYNC_STAGES-1 is the first stage (LSb). So no matter the number of stages, the last stage (synced) output is always sync_ff[0].
    always_ff @(negedge async_rst_i, posedge clk_i) begin
      if(async_rst_i != 1'b1) begin // Asynchronous part - assert reset
        sync_ff <= '0; 
      end else begin // Synchronous part - shift in '1's - deasserting reset
        sync_ff <= {sync_ff[1:SYNC_STAGES-1], 1'b1}; // Shift left, inserting '1' at LSb
      end
    end
  end else begin : GEN_SYNC_DEFAULT // If the reset is not specified accordingly, indicate a fatal error! Also fall to default behaviour - just pass it through (directly) 
    $fatal("ERROR in 'reset_sync': Invalid RESET_POLARITY parameter value! Supported values are: 'HIGH' and 'LOW'.");
    logic [0:SYNC_STAGES-1] sync_ff;
    assign sync_ff[0] = async_rst_i; // Directly pass through the async reset input to the output
  end
endgenerate 

assign synced_rst_o = sync_ff[0]; // Output the last stage of the synchronizer

endmodule

ex2/uart_led_btn/hdl_tb/reset_sync_tb.sv
// Testbench for reset synchronizer module
`timescale 1ns / 1ps // Note: the simulation time unit must be set to 1 [ns]

module reset_sync_tb;

  // =============================================================================
  // TESTBENCH PARAMETERS AND CONSTANTS
  // =============================================================================
  // Testbench parameters - matching DUT's:
  localparam CLK_FREQ = 50_000_000; // External Clock source, in [Hz]
  localparam CLK_PERIOD = 20;  // External Clock source, in [ns]
  localparam SYNC_STAGES = 2;   // Number of synchronization stages
  localparam RESET_POLARITY = "LOW"; // Reset polarity: "LOW" for active low reset 
  // Testbench parameters - for simulation:
  localparam SIMULATION_TIME = 100_000_000; // Simulation time in [ns]

  // =============================================================================
  // TESTBENCH SIGNALS
  // =============================================================================
  logic clk;              // Clock signal
  logic async_rst;        // Asynchronous reset input 
  logic synced_rst_low;   // Synchronized reset output - for active "low" config
  logic synced_rst_high;  // Synchronized reset output - for active "high" config

  integer unsigned fail_count = 0; // Test fail counter
  // =============================================================================
  // CLOCK GENERATION
  // =============================================================================
  initial begin
    clk = 1'b0;
    forever #(CLK_PERIOD / 2) clk = ~clk; // Toggle clock every half period
  end   

  // =============================================================================
  // UNIT UNDER TEST (UUT) INSTANTIATION
  // =============================================================================
  // DUT instantiation - Active LOW reset
  reset_sync #(
      .SYNC_STAGES(SYNC_STAGES),
      .RESET_POLARITY("LOW")
  ) UUT_ACTIVE_LOW (
      .clk_i(clk),
      .async_rst_i(async_rst),
      .synced_rst_o(synced_rst_low)
  );

  // DUT instantiation - Active HIGH reset
  reset_sync #(
      .SYNC_STAGES(SYNC_STAGES),
      .RESET_POLARITY("HIGH")
  ) UUT_ACTIVE_HIGH (
      .clk_i(clk),
      .async_rst_i(async_rst),
      .synced_rst_o(synced_rst_high)
  );

  // ============================================================================
  // TASKS AND FUNCTIONS
  // ============================================================================
  // (None needed for this testbench)

  // =============================================================================
  // TEST SEQUENCE
  // =============================================================================
  initial begin
    // Display testbench header information
    $display("========================================");
    $display("Reset Synchronizer Testbench Starting");
    $display("========================================");
    $display("Clock Frequency: %0d Hz", CLK_PERIOD);    
    $display("Clock Period: %0d ns", CLK_PERIOD);
    $display("Reset Polarity: %s", "Both LOW and HIGH");
    $display("Synchronization Stages: %0d", SYNC_STAGES);
    $display("");

    // Wait for a short time before starting tests - to observe initial conditions
    #10; 
  
    // Initialize
    async_rst = 0;
    
    // Wait for a few clock cycles
    repeat(5) @(posedge clk);
    
    // Test 1: Active-HIGH reset - Asynchronous assertion
    $display("Test 1: Active-HIGH Reset - Asynchronous Assertion");
    async_rst = 1;
    #1; // Small delay to see asynchronous effect
    $display("  t=%0t: async_rst asserted, synced_rst_high=%b (should be 1 immediately)", 
             $time, synced_rst_high);
    
    // Hold reset for a few cycles
    repeat(3) @(posedge clk);
    
    // Test 2: Active-HIGH reset - Synchronous deassertion
    $display("Test 2: Active-HIGH Reset - Synchronous Deassertion");
    @(posedge clk);
    async_rst = 0;
    $display("  t=%0t: async_rst deasserted at clock edge", $time);
    
    // Monitor deassertion through sync stages
    for(int i = 1; i <= SYNC_STAGES + 1; i++) begin
      @(posedge clk);
      $display("  t=%0t: Clock %0d after deassertion, synced_rst_high=%b", 
               $time, i, synced_rst_high);
    end
    
    // Verify full deassertion
    if(synced_rst_high == 0) begin
      $display("  PASS: Reset deasserted after %0d clock cycles", SYNC_STAGES);
    end else begin
      $display("  FAIL: Reset not deasserted properly!");
    end
    $display("");
    
    // Wait before next test
    repeat(5) @(posedge clk);
    
    // Test 3: Active-LOW reset - Asynchronous assertion
    $display("Test 3: Active-LOW Reset - Asynchronous Assertion");
    async_rst = 0;
    #1; // Small delay to see asynchronous effect
    $display("  t=%0t: async_rst asserted (LOW), synced_rst_low=%b (should be 0 immediately)", 
             $time, synced_rst_low);
    
    // Hold reset for a few cycles
    repeat(3) @(posedge clk);
    
    // Test 4: Active-LOW reset - Synchronous deassertion
    $display("Test 4: Active-LOW Reset - Synchronous Deassertion");
    @(posedge clk);
    async_rst = 1;
    $display("  t=%0t: async_rst deasserted (HIGH) at clock edge", $time);
    
    // Monitor deassertion through sync stages
    for(int i = 1; i <= SYNC_STAGES + 1; i++) begin
      @(posedge clk);
      $display("  t=%0t: Clock %0d after deassertion, synced_rst_low=%b", 
               $time, i, synced_rst_low);
    end
    
    // Verify full deassertion
    if(synced_rst_low == 1) begin
      $display("  PASS: Reset deasserted after %0d clock cycles", SYNC_STAGES);
    end else begin
      $display("  FAIL: Reset not deasserted properly!");
    end
    $display("");
    
    // Test 5: Metastability test - Assert reset near clock edge
    repeat(5) @(posedge clk);
    $display("Test 5: Metastability Test - Reset Toggle Near Clock Edge");
    async_rst = 0;
    #(CLK_PERIOD - 0.5); // Assert very close to clock edge
    async_rst = 1;
    #1;
    $display("  t=%0t: Reset toggled near clock edge", $time);
    repeat(SYNC_STAGES + 2) @(posedge clk);
    $display("  System stabilized, synced_rst_high=%b, synced_rst_low=%b", 
             synced_rst_high, synced_rst_low);
    $display("");
    
    // Test 6: Short pulse test
    repeat(5) @(posedge clk);
    $display("Test 6: Short Async Reset Pulse (< 1 clock cycle)");
    async_rst = 0;
    #(CLK_PERIOD/4); // Short pulse
    async_rst = 1;
    $display("  t=%0t: Short reset pulse applied", $time);
    repeat(SYNC_STAGES + 2) @(posedge clk);
    $display("  After sync stages, synced_rst_high=%b, synced_rst_low=%b", 
             synced_rst_high, synced_rst_low);
    $display("");
    
    // Final summary
    $display("========================================");
    $display("Testbench Completed Successfully");
    $display("========================================");
    
    #100;
    $finish;
  end
  
  // =============================================================================
  // WAVEFORM DUMPING 
  // =============================================================================
  initial begin
    $dumpfile("reset_sync_tb.vcd");
    $dumpvars(0, reset_sync_tb);
  end
  
  // =============================================================================
  // CONTINUOUS MONITORING (OPTIONAL DEBUG)
  // =============================================================================
  always @(synced_rst_high) begin
    $display("  [Monitor] t=%0t: synced_rst_high changed to %b", $time, synced_rst_high);
  end
  
  always @(synced_rst_low) begin
    $display("  [Monitor] t=%0t: synced_rst_low changed to %b", $time, synced_rst_low);
  end

endmodule

ex2/uart_led_btn/simulation/questa/reset_sync_tb.vcd
$date
	Sun Jan 25 18:54:39 2026
$end
$version
	QuestaSim Version 2024.1
$end
$timescale
	1ps
$end

$scope module reset_sync_tb $end
$var parameter 32 ! CLK_FREQ $end
$var parameter 32 " CLK_PERIOD $end
$var parameter 32 # SYNC_STAGES $end
$var parameter 24 $ RESET_POLARITY $end
$var parameter 32 % SIMULATION_TIME $end
$var reg 1 & clk $end
$var reg 1 ' async_rst $end
$var reg 1 ( synced_rst_low $end
$var reg 1 ) synced_rst_high $end
$var integer 32 * fail_count $end

$scope module UUT_ACTIVE_LOW $end
$var parameter 24 + RESET_POLARITY $end
$var parameter 32 , SYNC_STAGES $end
$var wire 1 - async_rst_i $end
$var wire 1 . clk_i $end
$var reg 1 / synced_rst_o $end
$var reg 2 0 sync_ff [0:1] $end

$scope begin GEN_SYNC_ACTIVE_LOW $end
$upscope $end
$upscope $end

$scope module UUT_ACTIVE_HIGH $end
$var parameter 32 1 RESET_POLARITY $end
$var parameter 32 2 SYNC_STAGES $end
$var wire 1 3 async_rst_i $end
$var wire 1 4 clk_i $end
$var reg 1 5 synced_rst_o $end
$var reg 2 6 sync_ff [0:1] $end

$scope begin GEN_SYNC_ACTIVE_HIGH $end
$upscope $end
$upscope $end
$upscope $end
$enddefinitions $end
#0
$dumpvars
0&
x'
x(
x)
x/
bx 0
x5
bx 6
b10111110101111000010000000 !
b10100 "
b10 #
b101111101011110000100000000 %
b10 ,
b10 2
b10011000100111101010111 $
b10011000100111101010111 +
b1001000010010010100011101001000 1
b0 *
04
x3
0.
x-
$end
#10000
1&
0'
1.
14
0-
03
bx0 6
b0 0
0/
0(
#20000
0&
0.
04
#30000
1&
1.
14
b0 6
05
0)
#40000
0&
0.
04
#50000
1&
1.
14
#60000
0&
0.
04
#70000
1&
1.
14
#80000
0&
0.
04
#90000
1&
1.
14
#100000
0&
0.
04
#110000
1&
1.
14
1'
1-
13
b11 6
15
1)
#120000
0&
0.
04
#130000
1&
1.
14
b1 0
#140000
0&
0.
04
#150000
1&
1.
14
b11 0
1/
1(
#160000
0&
0.
04
#170000
1&
1.
14
#180000
0&
0.
04
#190000
1&
1.
14
0'
0-
03
b0 0
0/
0(
#200000
0&
0.
04
#210000
1&
1.
14
b10 6
#220000
0&
0.
04
#230000
1&
1.
14
b0 6
05
0)
#240000
0&
0.
04
#250000
1&
1.
14
#260000
0&
0.
04
#270000
1&
1.
14
#280000
0&
0.
04
#290000
1&
1.
14
#300000
0&
0.
04
#310000
1&
1.
14
#320000
0&
0.
04
#330000
1&
1.
14
#340000
0&
0.
04
#350000
1&
1.
14
#360000
0&
0.
04
#370000
1&
1.
14
#380000
0&
0.
04
#390000
1&
1.
14
#400000
0&
0.
04
#410000
1&
1.
14
#420000
0&
0.
04
#430000
1&
1.
14
1'
1-
13
b11 6
15
1)
#440000
0&
0.
04
#450000
1&
1.
14
b1 0
#460000
0&
0.
04
#470000
1&
1.
14
b11 0
1/
1(
#480000
0&
0.
04
#490000
1&
1.
14
#500000
0&
0.
04
#510000
1&
1.
14
#520000
0&
0.
04
#530000
1&
1.
14
#540000
0&
0.
04
#550000
1&
1.
14
#560000
0&
0.
04
#570000
1&
1.
14
#580000
0&
0.
04
#590000
1&
1.
14
0'
0-
03
b0 0
0/
0(
#600000
0&
0.
04
#609500
1'
1-
13
#610000
1&
1.
14
b1 0
#620000
0&
0.
04
#630000
1&
1.
14
b11 0
1/
1(
#640000
0&
0.
04
#650000
1&
1.
14
#660000
0&
0.
04
#670000
1&
1.
14
#680000
0&
0.
04
#690000
1&
1.
14
#700000
0&
0.
04
#710000
1&
1.
14
#720000
0&
0.
04
#730000
1&
1.
14
#740000
0&
0.
04
#750000
1&
1.
14
#760000
0&
0.
04
#770000
1&
1.
14
#780000
0&
0.
04
#790000
1&
1.
14
0'
0-
03
b0 0
0/
0(
#795000
1'
1-
13
#800000
0&
0.
04
#810000
1&
1.
14
b1 0
#820000
0&
0.
04
#830000
1&
1.
14
b11 0
1/
1(
